os_remover/__init__.py
os_remover/linux.py
os_remover/macos.py
os_remover/mode_selector.py
os_remover/os_selector.py
os_remover/windows.py
os_remover-0.1.1.dist-info/METADATA
os_remover-0.1.1.dist-info/WHEEL
os_remover-0.1.1.dist-info/top_level.txt
os_remover-0.1.1.dist-info/RECORD
